{"id":15685,"rada_id":272,"gender":1,"surname":"Іщенко","firstname":"Валерій","patronymic":"Олександрович","district_num":null,"region_id":null,"num_in_party":37,"date_oath":"2014-11-27T00:00:00","resignation_date":null,"resignation_reason":null,"birthday":"1973-11-11T00:00:00","short_info":"народився 11 листопада 1973 року, громадянин України, протягом останніх п’яти років проживає на території України, освіта вища, народний депутат України, безпартійний, проживає в місті Києві, судимість відсутня, включений до виборчого списку під № 37.","photo":"http:\/\/static.rada.gov.ua\/dep_img8\/bp37.jpg","party_id":50,"convocation":8,"obr_info":"загальнодержавному багатомандатному округу<br>ПАРТІЯ \"БЛОК ПЕТРА ПОРОШЕНКА\"<br>Порядковий номер у списку 37","photo_ext":"jpg","presentAuto_present":464,"presentAuto_absent":40,"presentManualy_present":449,"presentManualy_absent":33,"presentManualy_confirmAbsent":19,"emails":[{"value":"Ishchenko.Valerii@rada.gov.ua"}],"phones":[{"value":"Тел: (044) 255-37-14"}],"assistants":[{"fullname":"Банас Дмитро Миколайович","type_id":4},{"fullname":"Чумак Юлія Ярославівна","type_id":4},{"fullname":"Гурбич Віктор Олексійович","type_id":4},{"fullname":"Бойко Ірина Ігорівна","type_id":2},{"fullname":"Лотоцький Микола Миколайович","type_id":2},{"fullname":"Артеменко Артем Васильович","type_id":4},{"fullname":"Новак Євгенія Леонідівна","type_id":4},{"fullname":"Балацій Ігор Миколайович","type_id":2}],"post_bfdas":[],"post_frs":[{"fr_post_id":918,"fr_association_id":2613},{"fr_post_id":8,"fr_association_id":2636}],"post_mps":[{"organization_id":52,"post_id":4},{"organization_id":62,"post_id":4},{"organization_id":39,"post_id":4},{"organization_id":7,"post_id":4},{"organization_id":80,"post_id":17},{"organization_id":293,"post_id":4},{"organization_id":29,"post_id":4}],"socials":[],"declarations":[{"post":"Народний депутат України","year":2013,"declarate_date":"2014-03-27T00:00:00","fullname":"Іщенко Валерій Олександрович","family_members":[{"decl_row_name_id":22,"relationship":"дружина","fullname":"Іщенко М.Г."},{"decl_row_name_id":22,"relationship":"дочка","fullname":"Іщенко В.В."}],"deposits":[{"sum_all":"12000","sum_abroad":null,"decl_row_name_id":71}],"financial_liabilities":[{"decl_row_name_id":74,"sum_all":"72894","sum_abroad":null}],"incomes":[{"decl_row_name_id":34,"sum_declarant":"129935","sum_family":null,"organizations":null},{"decl_row_name_id":23,"sum_declarant":"369141","sum_family":"43200","organizations":null},{"decl_row_name_id":24,"sum_declarant":"239206","sum_family":"43200","organizations":null}],"incomes_abroad":[{"decl_row_name_id":39,"sum_our":"129935","sum_abroad":"500000","country":"Російська Федерація"}],"realties":[{"decl_row_name_id":46,"sum_own":null,"sum_other":null,"area":"12,6 (машиномісце)"},{"decl_row_name_id":43,"sum_own":null,"sum_other":null,"area":"77,4"},{"decl_row_name_id":46,"sum_own":null,"sum_other":null,"area":"12,6 (машиномісце)"},{"decl_row_name_id":49,"sum_own":null,"sum_other":null,"area":"1\/6 від 89,2"},{"decl_row_name_id":43,"sum_own":null,"sum_other":null,"area":"128,4"}],"transports":[{"decl_row_name_id":58,"model":"Merсedes Benz  ML 350, 3498","year_create":2007,"sum_own":null,"sum_other":null}]},{"post":"народний депутат України","year":2014,"declarate_date":"2015-03-30T00:00:00","fullname":"Іщенко Валерій Олександрович","family_members":[{"decl_row_name_id":22,"relationship":"дружина","fullname":"Іщенко М.Г."},{"decl_row_name_id":22,"relationship":"донька","fullname":"Іщенко В.В."}],"deposits":[{"sum_all":"12000","sum_abroad":null,"decl_row_name_id":71}],"financial_liabilities":[{"decl_row_name_id":74,"sum_all":"84924","sum_abroad":null}],"incomes":[{"decl_row_name_id":23,"sum_declarant":"176362","sum_family":"48438","organizations":null},{"decl_row_name_id":24,"sum_declarant":"176362","sum_family":"48438","organizations":null}],"incomes_abroad":[],"realties":[{"decl_row_name_id":43,"sum_own":null,"sum_other":null,"area":"77,4"},{"decl_row_name_id":49,"sum_own":null,"sum_other":null,"area":"1\/6 від 89,2"},{"decl_row_name_id":46,"sum_own":null,"sum_other":null,"area":"12,6"},{"decl_row_name_id":46,"sum_own":null,"sum_other":null,"area":"12,6"},{"decl_row_name_id":43,"sum_own":null,"sum_other":null,"area":"128,4"}],"transports":[{"decl_row_name_id":58,"model":"Mercedes Benz ML 350; 3498","year_create":2007,"sum_own":null,"sum_other":null}]},{"post":"народний депутат України","year":2015,"declarate_date":"2016-03-31T00:00:00","fullname":"Іщенко Валерій Олександрович","family_members":[],"deposits":[{"sum_all":"414610","sum_abroad":null,"decl_row_name_id":64},{"sum_all":"414610","sum_abroad":null,"decl_row_name_id":63}],"financial_liabilities":[{"decl_row_name_id":74,"sum_all":"111910","sum_abroad":null}],"incomes":[{"decl_row_name_id":24,"sum_declarant":"78724","sum_family":null,"organizations":null},{"decl_row_name_id":23,"sum_declarant":"2078724","sum_family":null,"organizations":null},{"decl_row_name_id":34,"sum_declarant":"2000000","sum_family":null,"organizations":null}],"incomes_abroad":[],"realties":[{"decl_row_name_id":46,"sum_own":null,"sum_other":null,"area":"12,6"},{"decl_row_name_id":46,"sum_own":null,"sum_other":null,"area":"12,6"},{"decl_row_name_id":43,"sum_own":null,"sum_other":null,"area":"77,4"},{"decl_row_name_id":43,"sum_own":null,"sum_other":null,"area":"128,4"}],"transports":[]},{"post":null,"year":2015,"declarate_date":null,"fullname":"Іщенко Валерій Олександрович","family_members":[],"deposits":[],"financial_liabilities":[],"incomes":[],"incomes_abroad":[],"realties":[],"transports":[]},{"post":null,"year":2016,"declarate_date":null,"fullname":"Іщенко Валерій Олександрович","family_members":[],"deposits":[],"financial_liabilities":[],"incomes":[],"incomes_abroad":[],"realties":[],"transports":[]},{"post":null,"year":2017,"declarate_date":null,"fullname":"Іщенко Валерій Олександрович","family_members":[],"deposits":[],"financial_liabilities":[],"incomes":[],"incomes_abroad":[],"realties":[],"transports":[]}],"anketa_url":"http:\/\/itd.rada.gov.ua\/mps\/info\/page\/15685","visiting":{"present":455,"reasons_valide":19,"reasons_unknown":33},"voting":{"by":8788,"no_vote":5115,"against":14,"missing":1128,"abstained":609}}